LICENSE
MANIFEST.in
aws_cfn_resources_schemas/__init__.py
aws_cfn_resources_schemas/alexa-ask-skill.json
aws_cfn_resources_schemas/aws-accessanalyzer-analyzer.json
aws_cfn_resources_schemas/aws-acmpca-certificate.json
aws_cfn_resources_schemas/aws-acmpca-certificateauthority.json
aws_cfn_resources_schemas/aws-acmpca-certificateauthorityactivation.json
aws_cfn_resources_schemas/aws-acmpca-permission.json
aws_cfn_resources_schemas/aws-amazonmq-broker.json
aws_cfn_resources_schemas/aws-amazonmq-configuration.json
aws_cfn_resources_schemas/aws-amazonmq-configurationassociation.json
aws_cfn_resources_schemas/aws-amplify-app.json
aws_cfn_resources_schemas/aws-amplify-branch.json
aws_cfn_resources_schemas/aws-amplify-domain.json
aws_cfn_resources_schemas/aws-amplifyuibuilder-component.json
aws_cfn_resources_schemas/aws-amplifyuibuilder-theme.json
aws_cfn_resources_schemas/aws-apigateway-account.json
aws_cfn_resources_schemas/aws-apigateway-apikey.json
aws_cfn_resources_schemas/aws-apigateway-authorizer.json
aws_cfn_resources_schemas/aws-apigateway-basepathmapping.json
aws_cfn_resources_schemas/aws-apigateway-clientcertificate.json
aws_cfn_resources_schemas/aws-apigateway-deployment.json
aws_cfn_resources_schemas/aws-apigateway-documentationpart.json
aws_cfn_resources_schemas/aws-apigateway-documentationversion.json
aws_cfn_resources_schemas/aws-apigateway-domainname.json
aws_cfn_resources_schemas/aws-apigateway-gatewayresponse.json
aws_cfn_resources_schemas/aws-apigateway-method.json
aws_cfn_resources_schemas/aws-apigateway-model.json
aws_cfn_resources_schemas/aws-apigateway-requestvalidator.json
aws_cfn_resources_schemas/aws-apigateway-resource.json
aws_cfn_resources_schemas/aws-apigateway-restapi.json
aws_cfn_resources_schemas/aws-apigateway-stage.json
aws_cfn_resources_schemas/aws-apigateway-usageplan.json
aws_cfn_resources_schemas/aws-apigateway-usageplankey.json
aws_cfn_resources_schemas/aws-apigateway-vpclink.json
aws_cfn_resources_schemas/aws-apigatewayv2-api.json
aws_cfn_resources_schemas-2021.12.29.dist-info/LICENSE
aws_cfn_resources_schemas-2021.12.29.dist-info/WHEEL
aws_cfn_resources_schemas-2021.12.29.dist-info/METADATA
aws_cfn_resources_schemas-2021.12.29.dist-info/RECORD
